tttt/__init__.py
mahdi_mex-5.5.dist-info/METADATA
mahdi_mex-5.5.dist-info/WHEEL
mahdi_mex-5.5.dist-info/top_level.txt
mahdi_mex-5.5.dist-info/RECORD
