Metadata-Version: 2.1
Name: mahdi-mex
Version: 5.5
Summary: CLONING PIP COMMAND
